[
  {
    "id": 33238,
    "name": "Move or Melt Monterey|A Cheesy Guide to Jack",
    "investigatorId": "08007",
    "published": "2021-09-26T08:25:30-07:00",
    "favorites": 227,
    "likes": 282,
    "comments": 6,
    "version": "1.0"
  },
  {
    "id": 33251,
    "name": "Monetary Jack - Twinal Tap (Deck Guide)",
    "investigatorId": "08007",
    "published": "2021-09-26T14:50:01-07:00",
    "favorites": 200,
    "likes": 237,
    "comments": 31,
    "version": "1.0"
  },
  {
    "id": 35838,
    "name": "❄ 2 Packs Deck Guide : The Underworld Bullwhip",
    "investigatorId": "08007",
    "published": "2022-02-08T08:40:55-08:00",
    "favorites": 83,
    "likes": 101,
    "comments": 8,
    "version": "1.0"
  },
  {
    "id": 42215,
    "name": "Jack Brings Samples to the Lab|20k Series|Deck Guide",
    "investigatorId": "08007",
    "published": "2023-03-17T10:33:28-07:00",
    "favorites": 45,
    "likes": 75,
    "comments": 4,
    "version": "1.0"
  },
  {
    "id": 35640,
    "name": "Desenterrando Secretos (CORE + CONFINES DE LA TIERRA + GUÍA",
    "investigatorId": "08007",
    "published": "2022-01-26T17:53:11-08:00",
    "favorites": 62,
    "likes": 75,
    "comments": 2,
    "version": "1.0"
  },
  {
    "id": 35191,
    "name": "Monterey Jack: my definitive solo deck",
    "investigatorId": "08007",
    "published": "2022-01-03T09:00:32-08:00",
    "favorites": 34,
    "likes": 43,
    "comments": 2,
    "version": "1.0"
  },
  {
    "id": 34911,
    "name": "Monterrey Jack - Macarrones con tomate (0xp)",
    "investigatorId": "08007",
    "published": "2021-12-21T10:47:46-08:00",
    "favorites": 22,
    "likes": 32,
    "comments": 0,
    "version": "1.0"
  },
  {
    "id": 34911,
    "name": "Monterrey Jack - Macarrones con tomate (0xp)",
    "investigatorId": "08007",
    "published": "2021-12-21T10:47:46-08:00",
    "favorites": 22,
    "likes": 32,
    "comments": 0,
    "version": "1.0"
  },
  {
    "id": 33435,
    "name": "Monterey; Dashing Rogue or Studious Scholar?",
    "investigatorId": "08007",
    "published": "2021-10-07T09:34:21-07:00",
    "favorites": 18,
    "likes": 20,
    "comments": 1,
    "version": "1.0"
  },
  {
    "id": 44728,
    "name": "The Monterey Vacuum",
    "investigatorId": "08007",
    "published": "2023-09-11T11:05:03-07:00",
    "favorites": 6,
    "likes": 16,
    "comments": 0,
    "version": "1.0"
  }
]